{
  "kind": "movie",
  "sourceId": "10604086",
  "title": "封神第一部：朝歌风云",
  "originalTitle": "封神第一部 / 封神三部曲1",
  "year": "2023",
  "coverPath": "covers/movie/10604086.webp",
  "coverUrl": "https://img9.doubanio.com/view/photo/s_ratio_poster/public/p2895465725.webp",
  "doubanUrl": "https://movie.douban.com/subject/10604086/",
  "detailUrl": "/movie/10604086",
  "listSummary": "2023-07-15(大规模点映) / 2023-07-20(中国大陆) / 费翔 / 李雪健 / 黄渤 / 于适 / 陈牧驰 / 娜然 / 此沙 / 武亚凡 / 夏雨 / 袁泉 / 中国大陆 / 乌尔善 / 2023-07-15 21:30 / 148分钟 / 动作 / 战争 / 奇幻 / 古装 / 冉平 Ping Ran / 冉甲男 Jia-nan Ran / 乌尔善 Wuershan / 曹升 Sheng Cao / 汉语普通话",
  "rating": 4,
  "markedAt": "2023-08-05 13:37:50",
  "estimatedMarkedAtRange": null,
  "comment": "妲己不用背锅了",
  "metadata": [
    {
      "label": "Original Title",
      "value": "(2023)"
    },
    {
      "label": "Title",
      "value": "封神第一部：朝歌风云"
    },
    {
      "label": "Year",
      "value": "2023"
    },
    {
      "label": "导演",
      "value": "乌尔善"
    },
    {
      "label": "编剧",
      "value": "冉平 / 冉甲男 / 乌尔善 / 曹昇"
    },
    {
      "label": "主演",
      "value": "费翔 / 李雪健 / 黄渤 / 于适 / 陈牧驰 / 更多..."
    },
    {
      "label": "类型",
      "value": "动作 / 战争 / 奇幻 / 古装"
    },
    {
      "label": "制片国家/地区",
      "value": "中国大陆"
    },
    {
      "label": "语言",
      "value": "汉语普通话"
    },
    {
      "label": "上映日期",
      "value": "2023-07-20(中国大陆) / 2023-07-15(大规模点映)"
    },
    {
      "label": "片长",
      "value": "148分钟"
    },
    {
      "label": "又名",
      "value": "封神第一部 / 封神三部曲1 / 封神演义系列·龙之战 / 封神三部曲之妖乱国殇 / Creation of the Gods Ⅰ： Kingdom of Storms / Creation of the Gods Ⅰ"
    },
    {
      "label": "IMDb",
      "value": "tt6979756"
    }
  ],
  "externalLinks": [
    {
      "label": "Douban",
      "url": "https://movie.douban.com/subject/10604086/"
    }
  ]
}
