{
  "kind": "movie",
  "sourceId": "10741834",
  "title": "复仇者联盟2：奥创纪元",
  "originalTitle": "Avengers: Age of Ultron / 复仇者联盟2 / 复仇者联盟：奥创时代",
  "year": "2015",
  "coverPath": "covers/movie/10741834.webp",
  "coverUrl": "https://img3.doubanio.com/view/photo/s_ratio_poster/public/p2229594647.webp",
  "doubanUrl": "https://movie.douban.com/subject/10741834/",
  "detailUrl": "/movie/10741834",
  "listSummary": "2015-05-01(美国) / 2015-05-12(中国大陆) / 小罗伯特·唐尼 / 克里斯·埃文斯 / 克里斯·海姆斯沃斯 / 马克·鲁法洛 / 斯嘉丽·约翰逊 / 杰瑞米·雷纳 / 詹姆斯·斯派德 / 塞缪尔·杰克逊 / 唐·钱德尔 / 亚伦·泰勒-约翰逊 / 美国 / marvel.com/avengers / 乔斯·韦登 / 142分钟 / 复仇者联盟2：奥创纪元 / 动作 / 科幻 / 奇幻 / 冒险 / 乔斯·韦登 Joss Whedon / 斯坦·李 Stan Lee / 杰克·科比 Jack Kirby / 英语 / 韩语",
  "rating": 5,
  "markedAt": "2015-05-13 01:56:15",
  "estimatedMarkedAtRange": null,
  "comment": "Hulk 活活用脸挡了一套咏春………",
  "metadata": [],
  "externalLinks": [
    {
      "label": "Douban",
      "url": "https://movie.douban.com/subject/10741834/"
    }
  ]
}
