{
  "kind": "movie",
  "sourceId": "1304447",
  "title": "记忆碎片",
  "originalTitle": "Memento",
  "year": "2000",
  "coverPath": "covers/movie/1304447.jpg",
  "coverUrl": "https://img3.doubanio.com/view/photo/s_ratio_poster/public/p641688453.jpg",
  "doubanUrl": "https://movie.douban.com/subject/1304447/",
  "detailUrl": "/movie/1304447",
  "listSummary": "2000-09-05(威尼斯电影节) / 2000-10-20(英国) / 2001-05-25(美国) / 盖·皮尔斯 / 凯瑞-安·莫斯 / 乔·潘托里亚诺 / 小马克·布恩 / 拉什·费加 / 乔雅·福克斯 / 斯蒂芬·托布罗斯基 / 哈里特·桑塞姆·哈里斯 / 托马斯·列农 / 考乐姆·吉斯·雷尼 / 美国 / 克里斯托弗·诺兰 / 113分钟 / 记忆碎片 / 犯罪 / 剧情 / 悬疑 / 惊悚 / 克里斯托弗·诺兰 Christopher Nolan / 乔纳森·诺兰 Jonathan Nolan / 英语",
  "rating": 5,
  "markedAt": "2014-12-02",
  "estimatedMarkedAtRange": null,
  "comment": "多年后重新看了一遍，居然一点印象都没有",
  "metadata": [],
  "externalLinks": [
    {
      "label": "Douban",
      "url": "https://movie.douban.com/subject/1304447/"
    }
  ]
}
