{
  "kind": "movie",
  "sourceId": "1307847",
  "title": "兄弟连",
  "originalTitle": "Band of Brothers",
  "year": "2001",
  "coverPath": "covers/movie/1307847.webp",
  "coverUrl": "https://img3.doubanio.com/view/photo/s_ratio_poster/public/p1714777727.webp",
  "doubanUrl": "https://movie.douban.com/subject/1307847/",
  "detailUrl": "/movie/1307847",
  "listSummary": "2001-09-09(美国) / 戴米恩·路易斯 / 唐尼·沃尔伯格 / 朗·里维斯顿 / 马修·塞特尔 / 里克·沃登 / 弗兰克·约翰·休斯 / 大卫·休默 / 迈克尔·库立兹 / 斯科特·格瑞恩斯 / 施恩·泰勒 / 美国 / 英国 / www.hbo.com/band-of-brothers / 大卫·弗兰科尔 / 米凯尔·萨洛门 / 汤姆·汉克斯 / 大卫·李兰特 / 理查德·隆克瑞恩 / 大卫·努特尔 / 菲尔·奥尔登·罗宾森 / 托尼·杜 / 大卫·利兰 / 70分钟 / 兄弟连 / 剧情 / 动作 / 历史 / 战争 / Stephen Ambrose / 埃里克·博克 Erik Bork / E·马克斯·弗莱 E. Max Frye / 汤姆·汉克斯 Tom Hanks / 埃里克·延德雷森 Erik Jendresen / Bruce C. McKenna / 约翰·奥罗夫 John Orloff / 格雷厄姆·约斯特 Graham Yost / 英语 / 荷兰语 / 法语 / 德语 / 立陶宛语",
  "rating": 5,
  "markedAt": "2015-10-17",
  "estimatedMarkedAtRange": null,
  "comment": "十多年了，我终于看完兄弟连了！",
  "metadata": [],
  "externalLinks": [
    {
      "label": "Douban",
      "url": "https://movie.douban.com/subject/1307847/"
    }
  ]
}
