{
  "kind": "movie",
  "sourceId": "1401536",
  "title": "机动战士高达 逆袭的夏亚 機動戦士ガンダム 逆襲のシャア",
  "originalTitle": "(1988)",
  "year": "1988",
  "coverPath": "covers/movie/1401536.webp",
  "coverUrl": "https://img9.doubanio.com/view/photo/s_ratio_poster/public/p2549768986.webp",
  "doubanUrl": "https://movie.douban.com/subject/1401536/",
  "detailUrl": "/movie/1401536",
  "listSummary": "1988-03-12(日本) / 古谷彻 / 池田秀一 / 铃置洋孝 / 榊原良子 / 白石冬美 / 川村万梨阿 / 弥生美月 / 佐佐木望 / 山寺宏一 / 伊仓一惠 / 日本 / www.gundam-cca.net / 富野由悠季 / 120分钟 / 机动战士高达 逆袭的夏亚 / 剧情 / 动作 / 科幻 / 动画 / 战争 / 富野由悠季 Yoshiyuki Tomino / 日语",
  "rating": 5,
  "markedAt": "2021-06-18",
  "estimatedMarkedAtRange": null,
  "comment": "第二次看，第一次在电影院看，氛围太好了。UC这么完结简直完美。",
  "metadata": [
    {
      "label": "Original Title",
      "value": "(1988)"
    },
    {
      "label": "Title",
      "value": "机动战士高达 逆袭的夏亚 機動戦士ガンダム 逆襲のシャア"
    },
    {
      "label": "Year",
      "value": "1988"
    },
    {
      "label": "导演",
      "value": "富野由悠季"
    },
    {
      "label": "编剧",
      "value": "富野由悠季"
    },
    {
      "label": "主演",
      "value": "古谷彻 / 池田秀一 / 铃置洋孝 / 榊原良子 / 白石冬美 / 更多..."
    },
    {
      "label": "类型",
      "value": "剧情 / 动作 / 科幻 / 动画 / 战争"
    },
    {
      "label": "制片国家/地区",
      "value": "日本"
    },
    {
      "label": "语言",
      "value": "日语"
    },
    {
      "label": "上映日期",
      "value": "1988-03-12(日本)"
    },
    {
      "label": "片长",
      "value": "120分钟"
    },
    {
      "label": "又名",
      "value": "机动战士：马沙之反击 (港) / Kidō Senshi Gandamu Gyakushū no Shā / Mobile Suit Gundam Char's Counter Attack"
    },
    {
      "label": "IMDb",
      "value": "tt0095262"
    }
  ],
  "externalLinks": [
    {
      "label": "Douban",
      "url": "https://movie.douban.com/subject/1401536/"
    },
    {
      "label": "IMDb",
      "url": "https://www.imdb.com/title/tt0095262/"
    }
  ]
}
