{
  "kind": "movie",
  "sourceId": "1890787",
  "title": "心中有鬼",
  "originalTitle": "誓言 / The Matrimony",
  "year": "2007",
  "coverPath": "covers/movie/1890787.jpg",
  "coverUrl": "https://img1.doubanio.com/view/photo/s_ratio_poster/public/p2362572719.jpg",
  "doubanUrl": "https://movie.douban.com/subject/1890787/",
  "detailUrl": "/movie/1890787",
  "listSummary": "2007-02-08(中国大陆) / 黎明 / 刘若英 / 范冰冰 / 徐松子 / 郑毓芝 / 中国大陆 / 滕华涛 / 91分钟 / 剧情 / 恐怖 / 惊悚 / 张家鲁 Jialu Zhang / 杨倩玲 Sin Ling Yeung / 汉语普通话",
  "rating": 3,
  "markedAt": "2010-01-02",
  "estimatedMarkedAtRange": null,
  "comment": "比我想象的好看许多~",
  "metadata": [],
  "externalLinks": [
    {
      "label": "Douban",
      "url": "https://movie.douban.com/subject/1890787/"
    }
  ]
}
