{
  "kind": "movie",
  "sourceId": "1978709",
  "title": "黑天鹅",
  "originalTitle": "Black Swan / 夺命黑天鹅 / 霸王别鹅(豆友译名)",
  "year": "2010",
  "coverPath": "covers/movie/1978709.jpg",
  "coverUrl": "https://img9.doubanio.com/view/photo/s_ratio_poster/public/p2549648344.jpg",
  "doubanUrl": "https://movie.douban.com/subject/1978709/",
  "detailUrl": "/movie/1978709",
  "listSummary": "2010-09-01(威尼斯电影节) / 2010-12-17(美国) / 娜塔莉·波特曼 / 米拉·库尼斯 / 文森特·卡索 / 芭芭拉·赫希 / 薇诺娜·瑞德 / 本杰明·米派德 / 克塞尼亚·索罗 / 克里斯汀娜·安娜波 / 詹妮特·蒙哥马利 / 塞巴斯蒂安·斯坦 / 美国 / 达伦·阿伦诺夫斯基 / 108分钟 / 103分钟(威尼斯电影节) / 黑天鹅 / 剧情 / 惊悚 / 安德雷斯·海因斯 Andres Heinz / 马克·海曼 Mark Heyman / 约翰·J·麦克劳克林 John J. McLaughlin / 英语 / 法语 / 意大利语",
  "rating": 5,
  "markedAt": "2011-01-12",
  "estimatedMarkedAtRange": null,
  "comment": "内心深处一饰三角的一场天鹅湖，perfect!",
  "metadata": [],
  "externalLinks": [
    {
      "label": "Douban",
      "url": "https://movie.douban.com/subject/1978709/"
    }
  ]
}
