{
  "kind": "movie",
  "sourceId": "2052059",
  "title": "黑之契约者",
  "originalTitle": "DARKER THAN BLACK -黒の契約者- / 黑之契约者 / Kuro no Keiyakusha",
  "year": "2007",
  "coverPath": "covers/movie/2052059.jpg",
  "coverUrl": "https://img3.doubanio.com/view/photo/s_ratio_poster/public/p2917224507.jpg",
  "doubanUrl": "https://movie.douban.com/subject/2052059/",
  "detailUrl": "/movie/2052059",
  "listSummary": "2007-04-05(日本) / 木内秀信 / 福圆美里 / 泽木郁也 / 池田胜 / 水树奈奈 / 川上伦子 / 名冢佳织 / 丰口惠美 / 井上和彦 / 本田贵子 / 日本 / 冈村天斋 / 久保山英一 / 平向智子 / 鸟羽聪 / 安斋刚文 / 恒松圭 / 千叶大辅 / 金子伸吾 / 山本秀世 / 24分钟 / 黑之契约者 / 动画 / 动作 / 恐怖 / 科幻 / 惊悚 / 冈村天斋 Tensai Okamura / 野村祐一 Yuuichi Nomura / 菅正太郎 Shotaro Suga / 大西信介 Nobusuke Ônishi / 砂山藏澄 Sunayama Kurasumi / BONES / 日语",
  "rating": 5,
  "markedAt": "2010-03-24",
  "estimatedMarkedAtRange": null,
  "comment": "绝对是一个伟大的强大的不可替代的世界观…… 超有爱",
  "metadata": [],
  "externalLinks": [
    {
      "label": "Douban",
      "url": "https://movie.douban.com/subject/2052059/"
    }
  ]
}
