{
  "kind": "movie",
  "sourceId": "2063914",
  "title": "哥斯拉",
  "originalTitle": "Godzilla",
  "year": "2014",
  "coverPath": "covers/movie/2063914.jpg",
  "coverUrl": "https://img9.doubanio.com/view/photo/s_ratio_poster/public/p2185227574.jpg",
  "doubanUrl": "https://movie.douban.com/subject/2063914/",
  "detailUrl": "/movie/2063914",
  "listSummary": "2014-05-08(洛杉矶首映) / 2014-05-16(美国) / 2014-06-13(中国大陆) / 亚伦·泰勒-约翰逊 / 卡梅隆·CJ·亚当斯 / 渡边谦 / 布莱恩·克兰斯顿 / 伊丽莎白·奥尔森 / 卡森·波尔德 / 莎莉·霍金斯 / 朱丽叶·比诺什 / 大卫·斯特雷泽恩 / 理查德·T·琼斯 / 美国 / 日本 / 加里斯·爱德华斯 / 123分钟 / 哥斯拉 / 动作 / 科幻 / 冒险 / 灾难 / 麦克思·鲍伦斯坦 Max Borenstein / 戴夫·卡拉汉姆 Dave Callaham / 本多猪四郎 Ishirô Honda / 村田武雄 Takeo Murata / 香山滋 Shigeru Kayama / 弗兰克·德拉邦特 Frank Darabont / 大卫·S·高耶 David S. Goyer / 英语 / 日语",
  "rating": 3,
  "markedAt": "2014-06-16",
  "estimatedMarkedAtRange": null,
  "comment": "白老师本来只是个化学老师，卖冰毒成了海森伯格赚了不少钱，后来逃去日本研究核能什么的了，总的来说事业蒸蒸日上，结果老婆死了就2B了。至于小粉，后来好像是去开赛车了。",
  "metadata": [],
  "externalLinks": [
    {
      "label": "Douban",
      "url": "https://movie.douban.com/subject/2063914/"
    }
  ]
}
