{
  "kind": "movie",
  "sourceId": "25908051",
  "title": "间谍之桥",
  "originalTitle": "Bridge of Spies / 换谍者(港) / 间谍桥(台)",
  "year": "2015",
  "coverPath": "covers/movie/25908051.webp",
  "coverUrl": "https://img1.doubanio.com/view/photo/s_ratio_poster/public/p2247974249.webp",
  "doubanUrl": "https://movie.douban.com/subject/25908051/",
  "detailUrl": "/movie/25908051",
  "listSummary": "2015-10-16(美国) / 汤姆·汉克斯 / 马克·里朗斯 / 斯科特·谢帕德 / 艾米·莱安 / 塞巴斯蒂安·科赫 / 阿伦·阿尔达 / 奥斯汀·斯托维尔 / 比利·马格努森 / 伊芙·休森 / 杰西·普莱蒙 / 美国 / 德国 / 印度 / bridgeofspies.com / 史蒂文·斯皮尔伯格 / 141分钟 / 间谍之桥 / 剧情 / 传记 / 历史 / 马特·查曼 Matt Charman / 伊桑·科恩 Ethan Coen / 乔尔·科恩 Joel Coen / 英语 / 德语 / 俄语",
  "rating": 5,
  "markedAt": "2016-02-19 23:16:20",
  "estimatedMarkedAtRange": null,
  "comment": "好久没有这样气质的电影了，喜欢的不得了",
  "metadata": [],
  "externalLinks": [
    {
      "label": "Douban",
      "url": "https://movie.douban.com/subject/25908051/"
    }
  ]
}
