{
  "kind": "movie",
  "sourceId": "25966044",
  "title": "黑镜 第三季",
  "originalTitle": "Black Mirror Season 3",
  "year": "2016",
  "coverPath": "covers/movie/25966044.webp",
  "coverUrl": "https://img3.doubanio.com/view/photo/s_ratio_poster/public/p2493240932.webp",
  "doubanUrl": "https://movie.douban.com/subject/25966044/",
  "detailUrl": "/movie/25966044",
  "listSummary": "2016-10-21(美国) / 古古·姆巴塔-劳 / 麦肯兹·戴维斯 / 布莱丝·达拉斯·霍华德 / 凯莉·麦克唐纳 / 杰罗姆·弗林 / 埃里克斯·劳瑟 / 爱丽丝·伊芙 / 詹姆斯·诺顿 / 迈克尔·凯利 / 马拉基·卡比 / 美国 / 英国 / 欧文·哈里斯 / 乔·赖特 / 詹姆斯·瓦特金斯 / 雅各布·维尔布鲁根 / 詹姆斯·霍斯 / 丹·特拉亨伯格 / 黑镜 / 60分钟 / 89分钟(第六集) / 黑镜 / 剧情 / 科幻 / 惊悚 / 查理·布鲁克 Charlie Brooker / 拉什达·琼斯 Rashida Jones / 迈克尔·舒尔 Michael Schur / 英语",
  "rating": 5,
  "markedAt": "2018-01-07",
  "estimatedMarkedAtRange": null,
  "comment": "忘记标了",
  "metadata": [],
  "externalLinks": [
    {
      "label": "Douban",
      "url": "https://movie.douban.com/subject/25966044/"
    }
  ]
}
