{
  "kind": "movie",
  "sourceId": "26862259",
  "title": "乘风破浪",
  "originalTitle": null,
  "year": "2017",
  "coverPath": "covers/movie/26862259.webp",
  "coverUrl": "https://img3.doubanio.com/view/photo/s_ratio_poster/public/p2408407697.webp",
  "doubanUrl": "https://movie.douban.com/subject/26862259/",
  "detailUrl": "/movie/26862259",
  "listSummary": "2017-01-28(中国大陆) / 邓超 / 彭于晏 / 赵丽颖 / 董子健 / 金士杰 / 易小星 / 张本煜 / 李荣浩 / 高华阳 / 李淳 / 中国大陆 / 韩寒 / 102分钟 / 剧情 / 喜剧 / 韩寒 Han Han / 汉语普通话",
  "rating": 5,
  "markedAt": "2017-04-16",
  "estimatedMarkedAtRange": null,
  "comment": "妈的韩寒怎么这么屌",
  "metadata": [],
  "externalLinks": [
    {
      "label": "Douban",
      "url": "https://movie.douban.com/subject/26862259/"
    }
  ]
}
