{
  "kind": "movie",
  "sourceId": "3546034",
  "title": "寒蝉鸣泣之时·礼",
  "originalTitle": "ひぐらしのなく頃に 礼",
  "year": "2009",
  "coverPath": "covers/movie/3546034.jpg",
  "coverUrl": "https://img3.doubanio.com/view/photo/s_ratio_poster/public/p2325230472.jpg",
  "doubanUrl": "https://movie.douban.com/subject/3546034/",
  "detailUrl": "/movie/3546034",
  "listSummary": "2009-02-25(日本) / 保志总一朗 / 田村由香里 / 雪野五月 / 金井美香 / 中原麻衣 / 堀江由衣 / 小野大辅 / 丸山咏二 / 茶风林 / 小杉十郎太 / 日本 / 川濑敏文 / 山口祐司 / 吉田俊司 / 30分钟 / 寒蝉鸣泣之时·礼 / 剧情 / 动画 / 悬疑 / 惊悚 / 恐怖 / 龙骑士07 Ryukishi07 / 川濑敏文 Kawase Toshifumi / 日语 / 保志総一朗 / 中原麻衣 / 雪野五月 / かないみか / 田村ゆかり / 堀江由衣",
  "rating": 3,
  "markedAt": "2012-06-06",
  "estimatedMarkedAtRange": null,
  "comment": "三个故事都不咋的。。。",
  "metadata": [],
  "externalLinks": [
    {
      "label": "Douban",
      "url": "https://movie.douban.com/subject/3546034/"
    }
  ]
}
