{
  "kind": "movie",
  "sourceId": "36188176",
  "title": "超人",
  "originalTitle": "Superman / 超人：传承 / 超人：遗产",
  "year": "2025",
  "coverPath": "covers/movie/36188176.webp",
  "coverUrl": "https://img2.doubanio.com/view/photo/s_ratio_poster/public/p2922810871.webp",
  "doubanUrl": "https://movie.douban.com/subject/36188176/",
  "detailUrl": "/movie/36188176",
  "listSummary": "2025-07-09(中国台湾) / 2025-07-11(美国) / 2025-07-11(中国大陆) / 大卫·科伦斯韦 / 瑞秋·布罗斯纳安 / 尼古拉斯·霍尔特 / 埃迪·盖瑟吉 / 安东尼·卡里根 / 内森·菲利安 / 伊莎贝拉·莫塞德 / 斯凯勒·吉桑多 / 莎拉·桑帕伊奥 / 玛利亚·加布里埃拉·德法里亚 / 美国 / 詹姆斯·古恩 / 130分钟 / 超人 / 动作 / 科幻 / 奇幻 / 冒险 / 詹姆斯·古恩 James Gunn / 杰里·西格尔 Jerry Siegel / 乔·舒斯特 Joe Shuster / 英语",
  "rating": 2,
  "markedAt": "2025-07-14 01:12:33",
  "estimatedMarkedAtRange": null,
  "comment": "大超是我的神啊差一点成了星爵，我是万万不同意，丑化绿灯我也是一万个不同意。好你想探讨神一样的超级英雄站队国家和政治立场的母题，那你能不能严肃一点讨论，拿大超这么不痛不痒的摸两下算什么。Lois说我爱你的时候大超那个傻乎乎的笑容算什么！？超人爹妈成了封建糟粕算什么，求求了收了神通吧别拍了。",
  "metadata": [
    {
      "label": "Original Title",
      "value": "(2025)"
    },
    {
      "label": "Title",
      "value": "超人 Superman"
    },
    {
      "label": "Year",
      "value": "2025"
    },
    {
      "label": "导演",
      "value": "詹姆斯·古恩"
    },
    {
      "label": "编剧",
      "value": "詹姆斯·古恩 / 杰里·西格尔 / 乔·舒斯特"
    },
    {
      "label": "主演",
      "value": "大卫·科伦斯韦 / 瑞秋·布罗斯纳安 / 尼古拉斯·霍尔特 / 埃迪·盖瑟吉 / 安东尼·卡里根 / 更多..."
    },
    {
      "label": "类型",
      "value": "动作 / 科幻 / 奇幻 / 冒险"
    },
    {
      "label": "制片国家/地区",
      "value": "美国"
    },
    {
      "label": "语言",
      "value": "英语"
    },
    {
      "label": "上映日期",
      "value": "2025-07-11(美国/中国大陆) / 2025-07-09(中国台湾)"
    },
    {
      "label": "片长",
      "value": "130分钟"
    },
    {
      "label": "又名",
      "value": "超人：传承 / 超人：遗产 / Superman： Legacy"
    },
    {
      "label": "IMDb",
      "value": "tt5950044"
    }
  ],
  "externalLinks": [
    {
      "label": "Douban",
      "url": "https://movie.douban.com/subject/36188176/"
    }
  ]
}
