{
  "kind": "movie",
  "sourceId": "4014396",
  "title": "神奇四侠2015",
  "originalTitle": "Fantastic Four / 新神奇四侠 / 神奇4侠(港)",
  "year": "2015",
  "coverPath": "covers/movie/4014396.webp",
  "coverUrl": "https://img3.doubanio.com/view/photo/s_ratio_poster/public/p2239463272.webp",
  "doubanUrl": "https://movie.douban.com/subject/4014396/",
  "detailUrl": "/movie/4014396",
  "listSummary": "2015-08-07(美国) / 迈尔斯·特勒 / 凯特·玛拉 / 迈克尔·B·乔丹 / 杰米·贝尔 / 托比·凯贝尔 / 雷格·E·凯蒂 / 蒂姆·布雷克·尼尔森 / 玛丽·蕾切尔·达德利 / 唐·耶索 / 兰斯·E·尼克尔斯 / 美国 / 英国 / 德国 / www.fantasticfourmovie.com / 乔什·特兰克 / 100分钟 / 106分钟(法国) / 神奇四侠2015 / 动作 / 科幻 / 冒险 / 西蒙·金伯格 Simon Kinberg / 杰克·科比 Jack Kirby / 斯坦·李 Stan Lee / 乔什·特兰克 Josh Trank / 杰瑞米·斯莱特 Jeremy Slater / 英语",
  "rating": 3,
  "markedAt": "2015-11-09 01:10:18",
  "estimatedMarkedAtRange": null,
  "comment": "怎么对得起超喜欢旧版的我………",
  "metadata": [],
  "externalLinks": [
    {
      "label": "Douban",
      "url": "https://movie.douban.com/subject/4014396/"
    }
  ]
}
