{
  "kind": "movie",
  "sourceId": "6517421",
  "title": "惊天魔盗团",
  "originalTitle": "Now You See Me / 非常盗(港) / 出神入化(台)",
  "year": "2013",
  "coverPath": "covers/movie/6517421.jpg",
  "coverUrl": "https://img9.doubanio.com/view/photo/s_ratio_poster/public/p2151336415.jpg",
  "doubanUrl": "https://movie.douban.com/subject/6517421/",
  "detailUrl": "/movie/6517421",
  "listSummary": "2013-05-21(纽约首映) / 2013-05-31(美国) / 2013-10-10(中国大陆) / 杰西·艾森伯格 / 艾拉·菲舍尔 / 伍迪·哈里森 / 戴夫·弗兰科 / 马克·鲁法洛 / 梅拉尼·罗兰 / 摩根·弗里曼 / 迈克尔·凯恩 / 迈克尔·凯利 / 凯特芮娜·巴尔夫 / 美国 / 法国 / www.nowyouseememovie.com / 路易斯·莱特里尔 / 115分钟 / 125分钟(加长版) / 惊天魔盗团 / 剧情 / 犯罪 / 悬疑 / 鲍兹·亚金 Boaz Yakin / Edward Ricourt / 艾德·索罗门 Ed Solomon / 英语 / 法语",
  "rating": 4,
  "markedAt": "2013-10-20 23:26:55",
  "estimatedMarkedAtRange": null,
  "comment": "Mark你讲话慢点。。。",
  "metadata": [],
  "externalLinks": [
    {
      "label": "Douban",
      "url": "https://movie.douban.com/subject/6517421/"
    }
  ]
}
