{
  "kind": "music",
  "sourceId": "38391228",
  "title": "在這裡停一下",
  "originalTitle": "在这里停一下",
  "year": "2026",
  "coverPath": "covers/music/38391228.jpg",
  "coverUrl": "https://img9.doubanio.com/view/subject/s/public/s35442166.jpg",
  "doubanUrl": "https://music.douban.com/subject/38391228/",
  "detailUrl": "/music/38391228",
  "listSummary": "deca joins / 2026-03-23 / 专辑 / 数字(Digital) / 摇滚",
  "rating": 4,
  "markedAt": "2026-04-23 17:32:44",
  "estimatedMarkedAtRange": null,
  "comment": "有点进步，最喜欢《坐过站》和《地图》",
  "metadata": [
    {
      "label": "Original Title",
      "value": "在这里停一下"
    },
    {
      "label": "Title",
      "value": "在這裡停一下"
    },
    {
      "label": "又名",
      "value": "在这里停一下"
    },
    {
      "label": "流派",
      "value": "摇滚"
    },
    {
      "label": "专辑类型",
      "value": "专辑"
    },
    {
      "label": "介质",
      "value": "数字(Digital)"
    },
    {
      "label": "发行时间",
      "value": "2026-03-23"
    },
    {
      "label": "出版者",
      "value": "发现梦想"
    },
    {
      "label": "唱片数",
      "value": "1"
    }
  ],
  "externalLinks": [
    {
      "label": "Douban",
      "url": "https://music.douban.com/subject/38391228/"
    }
  ]
}
