{
  "kind": "book",
  "sourceId": "6434486",
  "title": "上帝掷骰子吗？",
  "originalTitle": null,
  "year": "2011",
  "coverPath": "covers/book/6434486.jpg",
  "coverUrl": "https://img1.doubanio.com/view/subject/s/public/s6475450.jpg",
  "doubanUrl": "https://book.douban.com/subject/6434486/",
  "detailUrl": "/book/6434486",
  "listSummary": "曹天元 / 辽宁教育出版社 / 2011-4-1 / 36.80元",
  "rating": 5,
  "markedAt": "2013-07-11",
  "estimatedMarkedAtRange": null,
  "comment": "太叼了！",
  "metadata": [
    {
      "label": "Title",
      "value": "上帝掷骰子吗？"
    },
    {
      "label": "作者",
      "value": "曹天元"
    },
    {
      "label": "出版社",
      "value": "辽宁教育出版社"
    },
    {
      "label": "出品方",
      "value": "磨铁图书"
    },
    {
      "label": "出版年",
      "value": "2011-4-1"
    },
    {
      "label": "ISBN",
      "value": "9787538291605"
    },
    {
      "label": "页数",
      "value": "356"
    },
    {
      "label": "装帧",
      "value": "平装"
    },
    {
      "label": "定价",
      "value": "36.80元"
    }
  ],
  "externalLinks": [
    {
      "label": "Douban",
      "url": "https://book.douban.com/subject/6434486/"
    }
  ]
}
